{
	"apiVersion": 2,
	"name": "prc-block/page",
	"category": "layout",
	"attributes": {
		"postId": {
            "type": "integer"
        },
		"title": {
            "type": "string"
        },
		"content": {
            "type": "string"
        },
		"url": {
            "type": "string"
        },
		"image": {
            "type": "string"
        },
		"enableExcerpt": {
            "type": "boolean",
			"default": true
		},
		"enableReadMore": {
            "type": "boolean",
			"default": false
        },
		"readMore": {
			"type": "string"
		}
    },
	"supports": {
		"html": false,
		"align": false,
		"inserter": false
	}
}
